{"6": {"var_loss": 0, "ideal_loss": 0, "closure_loss": 0, "shear_loss": 0, "curr_loss": 0.5722323911851285}, "7": {"var_loss": 0, "ideal_loss": 0, "closure_loss": 0, "shear_loss": 0, "curr_loss": 0.44205707328900407}, "8": {"var_loss": 0, "ideal_loss": 0, "closure_loss": 0, "shear_loss": 0, "curr_loss": 0.35655745418243745}, "9": {"var_loss": 0, "ideal_loss": 0, "closure_loss": 0, "shear_loss": 0, "curr_loss": 0.304621064560107}, "10": {"var_loss": 0, "ideal_loss": 0, "closure_loss": 0, "shear_loss": 0, "curr_loss": 0.37770704919012643}, "11": {"var_loss": 0, "ideal_loss": 0, "closure_loss": 0, "shear_loss": 0, "curr_loss": 0.2839700011321919}, "12": {"var_loss": 0, "ideal_loss": 0, "closure_loss": 0, "shear_loss": 0, "curr_loss": 0.34904987188619957}, "13": {"var_loss": 0, "ideal_loss": 0, "closure_loss": 0, "shear_loss": 0, "curr_loss": 0.5957883889999294}}